aiokeepin/__init__.py
aiokeepin/adapters/__init__.py
aiokeepin/adapters/base.py
aiokeepin/client.py
aiokeepin/exceptions/__init__.py
aiokeepin/exceptions/base.py
aiokeepin/utils/__init__.py
aiokeepin/utils/logging.py
aiokeepin-0.2.2.dist-info/LICENSE
aiokeepin-0.2.2.dist-info/METADATA
aiokeepin-0.2.2.dist-info/WHEEL
aiokeepin-0.2.2.dist-info/RECORD
