Metadata-Version: 2.1
Name: aiokeepin
Version: 0.2.2
Summary: Async python wrapper for KeepinCRM API
Home-page: https://github.com/radzih/aiokeepin
License: MIT
Keywords: keepin,keepincrm,api,wrapper,async,httpx,aiokeepin
Author: Vadim Radzih
Author-email: iphonevadim2003@gmail.com
Requires-Python: >=3.10,<4.0
Classifier: License :: OSI Approved :: MIT License
Classifier: Programming Language :: Python :: 3
Classifier: Programming Language :: Python :: 3.10
Classifier: Programming Language :: Python :: 3.11
Requires-Dist: httpx (>=0.24.0,<0.25.0)
Project-URL: Repository, https://github.com/radzih/aiokeepin
